[
  {
    "id": 1784473253814,
    "name": "调研与方案设计",
    "planDate": "2026-07-31",
    "status": "doing",
    "progress": 34,
    "moduleList": [
      {
        "id": 1784473253815,
        "name": "1.资产管理",
        "planFinishDate": "",
        "actualFinishDate": "",
        "progress": 60,
        "open": true,
        "levelOneTasks": [
          {
            "id": 1784473253816,
            "name": "1.业务流",
            "planFinishDate": "2026-07-17",
            "actualFinishDate": "2026-07-17",
            "progress": 100,
            "open": true,
            "levelTwoTasks": [
              {
                "id": 1784473253817,
                "name": "资产L1流程调研",
                "planFinishDate": "2026-07-03",
                "actualFinishDate": "2026-07-03",
                "progress": 100
              },
              {
                "id": 1784473253818,
                "name": "资产档案专题调研（分阶段上传复核流程",
                "planFinishDate": "2026-07-17",
                "actualFinishDate": "2026-07-17",
                "progress": 100
              }
            ],
            "autoPlanDate": true,
            "autoActualDate": true
          },
          {
            "id": 1784473253820,
            "name": "2.数据流",
            "planFinishDate": "2026-07-23",
            "actualFinishDate": "",
            "progress": 73,
            "open": true,
            "levelTwoTasks": [
              {
                "id": 1784473253821,
                "name": "电站/公司/客户主数据表",
                "planFinishDate": "2026-07-09",
                "actualFinishDate": "2026-07-09",
                "progress": 100
              },
              {
                "id": 1784473253822,
                "name": "主数据专题调研",
                "planFinishDate": "2026-07-13",
                "actualFinishDate": "2026-07-13",
                "progress": 100
              },
              {
                "id": 1784473253823,
                "name": "合同/保单收集关键字段提炼",
                "planFinishDate": "2026-07-17",
                "actualFinishDate": "",
                "progress": 30
              },
              {
                "id": 1784473253824,
                "name": "确定大文件存储方案//IDC文件服务器",
                "planFinishDate": "2026-07-23",
                "actualFinishDate": "2026-07-20",
                "progress": 99
              },
              {
                "id": 1784473253825,
                "name": "确定OA附件是否支持同步//支持但OA附件无法关联项目和清单分类",
                "planFinishDate": "2026-07-23",
                "actualFinishDate": "2026-07-20",
                "progress": 100
              },
              {
                "id": 1784473253826,
                "name": "资产评价报告模版梳理",
                "planFinishDate": "2026-07-23",
                "actualFinishDate": "",
                "progress": 55
              },
              {
                "id": 1784473253827,
                "name": "提供973资产清单-折旧规则对齐",
                "planFinishDate": "2026-07-23",
                "actualFinishDate": "",
                "progress": 100
              },
              {
                "id": 1784473253828,
                "name": "欣通云-场站映射方案",
                "planFinishDate": "",
                "actualFinishDate": "",
                "progress": 22
              },
              {
                "id": 1784507778496,
                "name": "项目档案上传涵盖建设前项目//与流程部评估上传方案",
                "planFinishDate": "",
                "actualFinishDate": "",
                "progress": 55
              }
            ],
            "autoPlanDate": true,
            "autoActualDate": false
          },
          {
            "id": 1784473253829,
            "name": "3.原型设计",
            "planFinishDate": "",
            "actualFinishDate": "",
            "progress": 65,
            "open": true,
            "levelTwoTasks": [
              {
                "id": 1784473253830,
                "name": "线框图思路",
                "planFinishDate": "2026-07-09",
                "actualFinishDate": "2026-07-09",
                "progress": 100
              },
              {
                "id": 1784473253831,
                "name": "高保真原型+4A图",
                "planFinishDate": "2026-07-24",
                "actualFinishDate": "",
                "progress": 30
              }
            ],
            "autoPlanDate": true,
            "autoActualDate": true
          },
          {
            "id": 1784473253832,
            "name": "4.接口设计",
            "planFinishDate": "",
            "actualFinishDate": "",
            "progress": 0,
            "open": false,
            "levelTwoTasks": [
              {
                "id": 1784473253833,
                "name": "欣通云接口需求清单",
                "planFinishDate": "2026-07-24",
                "actualFinishDate": "",
                "progress": 0
              }
            ],
            "autoPlanDate": true,
            "autoActualDate": true
          }
        ]
      },
      {
        "id": 1784473253834,
        "name": "2.结算管理",
        "planFinishDate": "",
        "actualFinishDate": "",
        "progress": 70,
        "open": true,
        "levelOneTasks": [
          {
            "id": 1784473253835,
            "name": "1. 业务流程",
            "planFinishDate": "",
            "actualFinishDate": "",
            "progress": 100,
            "open": false,
            "levelTwoTasks": [
              {
                "id": 1784473253836,
                "name": "结算流程梳理",
                "planFinishDate": "2026-07-15",
                "actualFinishDate": "",
                "progress": 100
              },
              {
                "id": 1784473253837,
                "name": "ERP/财务共享系统联动调研",
                "planFinishDate": "2026-07-15",
                "actualFinishDate": "",
                "progress": 100
              },
              {
                "id": 1784473253838,
                "name": "欣通数据对接专题调研",
                "planFinishDate": "2026-07-16",
                "actualFinishDate": "",
                "progress": 100
              }
            ],
            "autoPlanDate": true,
            "autoActualDate": true
          },
          {
            "id": 1784473253839,
            "name": "2. 数据流",
            "planFinishDate": "2026-07-24",
            "actualFinishDate": "",
            "progress": 74,
            "open": true,
            "levelTwoTasks": [
              {
                "id": 1784473253840,
                "name": "项目结算单表单模板收集",
                "planFinishDate": "2026-07-24",
                "actualFinishDate": "",
                "progress": 100
              },
              {
                "id": 1784473253841,
                "name": "分析结算单电量电价来源及公式",
                "planFinishDate": "2026-07-23",
                "actualFinishDate": "",
                "progress": 55
              },
              {
                "id": 1784473253842,
                "name": "ERP-关联成本科目-同步成本数据方案",
                "planFinishDate": "2026-07-22",
                "actualFinishDate": "",
                "progress": 55
              },
              {
                "id": 1784473253843,
                "name": "ERP-法人主体客户在ERP/运营系统的建档方式//建档后同步",
                "planFinishDate": "2026-07-22",
                "actualFinishDate": "",
                "progress": 90
              },
              {
                "id": 1784473253844,
                "name": "财务待办-完善成本科目、应收凭证科目、导出ERP项目数据",
                "planFinishDate": "2026-07-22",
                "actualFinishDate": "",
                "progress": 99
              },
              {
                "id": 1784473253845,
                "name": "财务共享&运营系统法人主体、客户编码对齐",
                "planFinishDate": "2026-07-22",
                "actualFinishDate": "",
                "progress": 99
              },
              {
                "id": 1784473253846,
                "name": "财务共享-开票信息推送方式//按标准接口字段推送，发票对应回款后推送通知；",
                "planFinishDate": "2026-07-22",
                "actualFinishDate": "",
                "progress": 100
              },
              {
                "id": 1784473253847,
                "name": "财务共享-973以外项目的法人主体建档",
                "planFinishDate": "2026-07-24",
                "actualFinishDate": "",
                "progress": 0
              },
              {
                "id": 1784473253848,
                "name": "欣通云-场站数据映射方案",
                "planFinishDate": "2026-07-24",
                "actualFinishDate": "",
                "progress": 55
              },
              {
                "id": 1784616715380,
                "name": "数据流转图-ERP/财务共享/运营系统",
                "planFinishDate": "2026-07-22",
                "actualFinishDate": "",
                "progress": 88
              }
            ],
            "autoPlanDate": true,
            "autoActualDate": true
          },
          {
            "id": 1784473253849,
            "name": "3.原型设计",
            "planFinishDate": "",
            "actualFinishDate": "",
            "progress": 50,
            "open": false,
            "levelTwoTasks": [
              {
                "id": 1784473253850,
                "name": "线框图",
                "planFinishDate": "2026-07-10",
                "actualFinishDate": "",
                "progress": 100
              },
              {
                "id": 1784473253851,
                "name": "高保真原型+4A图",
                "planFinishDate": "2026-07-17",
                "actualFinishDate": "",
                "progress": 0
              }
            ],
            "autoPlanDate": true,
            "autoActualDate": true
          },
          {
            "id": 1784473253852,
            "name": "4. 接口清单",
            "planFinishDate": "",
            "actualFinishDate": "",
            "progress": 54,
            "open": true,
            "levelTwoTasks": [
              {
                "id": 1784473253853,
                "name": "欣通云接口需求清单",
                "planFinishDate": "2026-07-24",
                "actualFinishDate": "",
                "progress": 88
              },
              {
                "id": 1784473253854,
                "name": "ERP/财务共享接口：应收应付凭证接口、开票申请接口",
                "planFinishDate": "2026-07-24",
                "actualFinishDate": "",
                "progress": 20
              }
            ],
            "autoPlanDate": true,
            "autoActualDate": true
          }
        ]
      },
      {
        "id": 1784473253855,
        "name": "3.运营监控",
        "planFinishDate": "",
        "actualFinishDate": "",
        "progress": 0,
        "open": true,
        "levelOneTasks": [
          {
            "id": 1784473253856,
            "name": "2.数据源",
            "planFinishDate": "",
            "actualFinishDate": "",
            "progress": 0,
            "open": true,
            "levelTwoTasks": [
              {
                "id": 1784473253857,
                "name": "欣通云-故障时长、SOC、SOH效能数据获取",
                "planFinishDate": "",
                "actualFinishDate": "",
                "progress": 0
              },
              {
                "id": 1784473253858,
                "name": "欣通云-设备运行数据指标",
                "planFinishDate": "",
                "actualFinishDate": "",
                "progress": 0
              }
            ],
            "autoPlanDate": true,
            "autoActualDate": true
          },
          {
            "id": 1784473253859,
            "name": "3.原型设计",
            "planFinishDate": "",
            "actualFinishDate": "",
            "progress": 0,
            "open": true,
            "levelTwoTasks": [
              {
                "id": 1784473253860,
                "name": "高保真原型+4A图",
                "planFinishDate": "2026-07-24",
                "actualFinishDate": "",
                "progress": 0
              }
            ],
            "autoPlanDate": true,
            "autoActualDate": true
          },
          {
            "id": 1784473253861,
            "name": "4.接口需求",
            "planFinishDate": "",
            "actualFinishDate": "",
            "progress": 0,
            "open": true,
            "levelTwoTasks": [
              {
                "id": 1784473253862,
                "name": "欣通云平台接口需求清单",
                "planFinishDate": "2026-07-24",
                "actualFinishDate": "",
                "progress": 0
              }
            ],
            "autoPlanDate": true,
            "autoActualDate": true
          }
        ]
      },
      {
        "id": 1784473253863,
        "name": "4.核容测算",
        "planFinishDate": "",
        "actualFinishDate": "",
        "progress": 38,
        "open": true,
        "levelOneTasks": [
          {
            "id": 1784473253864,
            "name": "1.流程",
            "planFinishDate": "",
            "actualFinishDate": "",
            "progress": 100,
            "open": true,
            "levelTwoTasks": [
              {
                "id": 1784473253865,
                "name": "核容流程调研",
                "planFinishDate": "",
                "actualFinishDate": "",
                "progress": 100
              },
              {
                "id": 1784473253866,
                "name": "剔除投建核容模块",
                "planFinishDate": "",
                "actualFinishDate": "",
                "progress": 100
              }
            ],
            "autoPlanDate": true,
            "autoActualDate": true
          },
          {
            "id": 1784473253867,
            "name": "2.数据源",
            "planFinishDate": "",
            "actualFinishDate": "",
            "progress": 0,
            "open": false,
            "levelTwoTasks": [
              {
                "id": 1784473253868,
                "name": "2.数据源",
                "planFinishDate": "",
                "actualFinishDate": "",
                "progress": 0
              }
            ],
            "autoPlanDate": true,
            "autoActualDate": true
          },
          {
            "id": 1784473253869,
            "name": "3.原型设计",
            "planFinishDate": "",
            "actualFinishDate": "",
            "progress": 0,
            "open": false,
            "levelTwoTasks": [
              {
                "id": 1784473253870,
                "name": "3.原型设计",
                "planFinishDate": "",
                "actualFinishDate": "",
                "progress": 0
              }
            ],
            "autoPlanDate": true,
            "autoActualDate": true
          },
          {
            "id": 1784473253871,
            "name": "4.接口需求",
            "planFinishDate": "",
            "actualFinishDate": "",
            "progress": 50,
            "open": true,
            "levelTwoTasks": [
              {
                "id": 1784473253872,
                "name": "4.接口需求",
                "planFinishDate": "",
                "actualFinishDate": "",
                "progress": 11
              },
              {
                "id": 1784473253873,
                "name": "投资测算-可行性、投前模型用历史数据测复盘irr",
                "planFinishDate": "",
                "actualFinishDate": "",
                "progress": 88
              }
            ],
            "autoPlanDate": true,
            "autoActualDate": true
          }
        ]
      },
      {
        "id": 1784473253874,
        "name": "5.运营策略",
        "planFinishDate": "",
        "actualFinishDate": "",
        "progress": 4,
        "open": false,
        "levelOneTasks": [
          {
            "id": 1784473253875,
            "name": "1.流程",
            "planFinishDate": "",
            "actualFinishDate": "",
            "progress": 15,
            "open": true,
            "levelTwoTasks": [
              {
                "id": 1784473253876,
                "name": "运维系统控制能力调研",
                "planFinishDate": "",
                "actualFinishDate": "",
                "progress": 30
              },
              {
                "id": 1784473253877,
                "name": "欣通控制策略格式",
                "planFinishDate": "",
                "actualFinishDate": "",
                "progress": 0
              }
            ],
            "autoPlanDate": true,
            "autoActualDate": true
          },
          {
            "id": 1784473253878,
            "name": "2.数据源",
            "planFinishDate": "",
            "actualFinishDate": "",
            "progress": 0,
            "open": false,
            "levelTwoTasks": [
              {
                "id": 1784473253879,
                "name": "2.数据源",
                "planFinishDate": "",
                "actualFinishDate": "",
                "progress": 0
              }
            ],
            "autoPlanDate": true,
            "autoActualDate": true
          },
          {
            "id": 1784473253880,
            "name": "3.原型设计",
            "planFinishDate": "",
            "actualFinishDate": "",
            "progress": 0,
            "open": false,
            "levelTwoTasks": [
              {
                "id": 1784473253881,
                "name": "3.原型设计",
                "planFinishDate": "",
                "actualFinishDate": "",
                "progress": 0
              }
            ],
            "autoPlanDate": true,
            "autoActualDate": true
          },
          {
            "id": 1784473253882,
            "name": "4.接口需求",
            "planFinishDate": "",
            "actualFinishDate": "",
            "progress": 0,
            "open": false,
            "levelTwoTasks": [
              {
                "id": 1784473253883,
                "name": "4.接口需求",
                "planFinishDate": "",
                "actualFinishDate": "",
                "progress": 0
              }
            ],
            "autoPlanDate": true,
            "autoActualDate": true
          }
        ]
      }
    ]
  },
  {
    "id": 1784473253884,
    "name": "业务蓝图阶段",
    "planDate": "2026-08-05",
    "status": "wait",
    "progress": 0,
    "moduleList": [
      {
        "id": 1784473253885,
        "name": "蓝图方案评审",
        "planFinishDate": "",
        "actualFinishDate": "",
        "progress": 0,
        "open": false,
        "levelOneTasks": [
          {
            "id": 1784473253886,
            "name": "蓝图方案评审",
            "planFinishDate": "",
            "actualFinishDate": "",
            "progress": 0,
            "open": false,
            "levelTwoTasks": [
              {
                "id": 1784473253887,
                "name": "蓝图方案评审",
                "planFinishDate": "",
                "actualFinishDate": "",
                "progress": 0
              }
            ],
            "autoPlanDate": true,
            "autoActualDate": true
          }
        ]
      }
    ]
  },
  {
    "id": 1784473253888,
    "name": "系统开发与实施",
    "planDate": "2026-10-31",
    "status": "doing",
    "progress": 13,
    "moduleList": [
      {
        "id": 1784473253889,
        "name": "环境搭建与系统集成",
        "planFinishDate": "",
        "actualFinishDate": "",
        "progress": 88,
        "open": true,
        "levelOneTasks": [
          {
            "id": 1784473253890,
            "name": "开发测试环境搭建",
            "planFinishDate": "",
            "actualFinishDate": "",
            "progress": 100,
            "open": true,
            "levelTwoTasks": [
              {
                "id": 1784473253891,
                "name": "资源申请开通",
                "planFinishDate": "2026-07-06",
                "actualFinishDate": "2026-07-06",
                "progress": 100
              },
              {
                "id": 1784473253892,
                "name": "中间件/数据库搭建",
                "planFinishDate": "2026-07-06",
                "actualFinishDate": "2026-07-10",
                "progress": 100
              },
              {
                "id": 1784473253893,
                "name": "运行环境搭建（代码部署）",
                "planFinishDate": "2026-07-10",
                "actualFinishDate": "2026-07-15",
                "progress": 100
              },
              {
                "id": 1784473253894,
                "name": "集成环境调试",
                "planFinishDate": "2026-07-15",
                "actualFinishDate": "2026-07-16",
                "progress": 100
              }
            ],
            "autoPlanDate": true,
            "autoActualDate": true
          },
          {
            "id": 1784473253895,
            "name": "技术方案",
            "planFinishDate": "2026-07-17",
            "actualFinishDate": "",
            "progress": 75,
            "open": true,
            "levelTwoTasks": [
              {
                "id": 1784473253896,
                "name": "PaaS-E端B端账号方案",
                "planFinishDate": "2026-07-14",
                "actualFinishDate": "",
                "progress": 50
              },
              {
                "id": 1784473253897,
                "name": "MK流程引擎对接方案",
                "planFinishDate": "2026-07-17",
                "actualFinishDate": "",
                "progress": 100
              }
            ],
            "autoPlanDate": true,
            "autoActualDate": true
          }
        ]
      },
      {
        "id": 1784473253899,
        "name": "集团底座集成",
        "planFinishDate": "",
        "actualFinishDate": "",
        "progress": 0,
        "open": false,
        "levelOneTasks": [
          {
            "id": 1784473253900,
            "name": "PaaS-接口对接",
            "planFinishDate": "2026-07-24",
            "actualFinishDate": "",
            "progress": 0,
            "open": false,
            "levelTwoTasks": [
              {
                "id": 1784473253901,
                "name": "二级细分任务",
                "planFinishDate": "",
                "actualFinishDate": "",
                "progress": 0
              }
            ],
            "autoPlanDate": false,
            "autoActualDate": true
          }
        ]
      },
      {
        "id": 1784507778491,
        "name": "新建功能模块",
        "planFinishDate": "",
        "actualFinishDate": "",
        "progress": 0,
        "open": false,
        "levelOneTasks": []
      },
      {
        "id": 1784507778492,
        "name": "新建功能模块",
        "planFinishDate": "",
        "actualFinishDate": "",
        "progress": 0,
        "open": false,
        "levelOneTasks": []
      },
      {
        "id": 1784507778493,
        "name": "新建功能模块",
        "planFinishDate": "",
        "actualFinishDate": "",
        "progress": 0,
        "open": false,
        "levelOneTasks": []
      },
      {
        "id": 1784507778494,
        "name": "新建功能模块",
        "planFinishDate": "",
        "actualFinishDate": "",
        "progress": 0,
        "open": false,
        "levelOneTasks": []
      },
      {
        "id": 1784507778495,
        "name": "新建功能模块",
        "planFinishDate": "",
        "actualFinishDate": "",
        "progress": 0,
        "open": false,
        "levelOneTasks": []
      }
    ]
  },
  {
    "id": 1784473253902,
    "name": "系统测试（SIT）",
    "planDate": "",
    "status": "wait",
    "progress": 0,
    "moduleList": [
      {
        "id": 1784473253903,
        "name": "新建功能模块",
        "planFinishDate": "",
        "actualFinishDate": "",
        "progress": 0,
        "open": false,
        "levelOneTasks": [
          {
            "id": 1784473253904,
            "name": "一级主任务",
            "planFinishDate": "",
            "actualFinishDate": "",
            "progress": 0,
            "open": false,
            "levelTwoTasks": [
              {
                "id": 1784473253905,
                "name": "二级细分任务",
                "planFinishDate": "",
                "actualFinishDate": "",
                "progress": 0
              }
            ],
            "autoPlanDate": true,
            "autoActualDate": true
          }
        ]
      }
    ]
  },
  {
    "id": 1784473253906,
    "name": "用户培训与UAT测试",
    "planDate": "",
    "status": "wait",
    "progress": 0,
    "moduleList": [
      {
        "id": 1784473253907,
        "name": "新建功能模块",
        "planFinishDate": "",
        "actualFinishDate": "",
        "progress": 0,
        "open": false,
        "levelOneTasks": [
          {
            "id": 1784473253908,
            "name": "一级主任务",
            "planFinishDate": "",
            "actualFinishDate": "",
            "progress": 0,
            "open": false,
            "levelTwoTasks": [
              {
                "id": 1784473253909,
                "name": "二级细分任务",
                "planFinishDate": "",
                "actualFinishDate": "",
                "progress": 0
              }
            ],
            "autoPlanDate": true,
            "autoActualDate": true
          }
        ]
      }
    ]
  },
  {
    "id": 1784473253910,
    "name": "上线试运行",
    "planDate": "",
    "status": "wait",
    "progress": 0,
    "moduleList": [
      {
        "id": 1784473253911,
        "name": "新建功能模块",
        "planFinishDate": "",
        "actualFinishDate": "",
        "progress": 0,
        "open": false,
        "levelOneTasks": [
          {
            "id": 1784473253912,
            "name": "一级主任务",
            "planFinishDate": "",
            "actualFinishDate": "",
            "progress": 0,
            "open": false,
            "levelTwoTasks": [
              {
                "id": 1784473253913,
                "name": "二级细分任务",
                "planFinishDate": "",
                "actualFinishDate": "",
                "progress": 0
              }
            ],
            "autoPlanDate": true,
            "autoActualDate": true
          }
        ]
      }
    ]
  },
  {
    "id": 1784473253914,
    "name": "项目验收",
    "planDate": "",
    "status": "wait",
    "progress": 0,
    "moduleList": [
      {
        "id": 1784473253915,
        "name": "新建功能模块",
        "planFinishDate": "",
        "actualFinishDate": "",
        "progress": 0,
        "open": false,
        "levelOneTasks": [
          {
            "id": 1784473253916,
            "name": "一级主任务",
            "planFinishDate": "",
            "actualFinishDate": "",
            "progress": 0,
            "open": false,
            "levelTwoTasks": [
              {
                "id": 1784473253917,
                "name": "二级细分任务",
                "planFinishDate": "",
                "actualFinishDate": "",
                "progress": 0
              },
              {
                "id": 1784473253918,
                "name": "二级细分任务",
                "planFinishDate": "",
                "actualFinishDate": "",
                "progress": 0
              }
            ],
            "autoPlanDate": true,
            "autoActualDate": true
          }
        ]
      }
    ]
  }
]